ChatbotAPI/__init__.py
ChatbotAPI/chatbasics.py
ChatbotAPI/errors.py
ChatbotAPI/test_main.py
ChatbotAPI/utils.py
ChatbotAPI-2.5.dist-info/LICENSE
ChatbotAPI-2.5.dist-info/METADATA
ChatbotAPI-2.5.dist-info/WHEEL
ChatbotAPI-2.5.dist-info/top_level.txt
ChatbotAPI-2.5.dist-info/RECORD
