Metadata-Version: 2.1
Name: ChatbotAPI
Version: 2.5
Summary: Library to make AI chatbot with other additional utilities
Home-page: https://github.com/hilfing/ChatbotAPI
Author: HilFing
Author-email: indradip.paul@outlook.com
Project-URL: Bug Tracker, https://github.com/hilfing/ChatbotAPI/issues
Project-URL: Wiki, https://github.com/hilfing/ChatbotAPI/wiki/Python
Classifier: Programming Language :: Python :: 3.13
Classifier: License :: OSI Approved :: GNU General Public License v3 (GPLv3)
Classifier: Operating System :: OS Independent
Classifier: Intended Audience :: Developers
Classifier: Environment :: Console
Classifier: Natural Language :: English
Requires-Python: >=3
License-File: LICENSE
Requires-Dist: requests
Requires-Dist: pyjokes
Requires-Dist: textblob
